{
	"configurations" : 
	[
		{
			"directories" : 
			[
				{
					"build" : ".",
					"childIndexes" : 
					[
						1
					],
					"hasInstallRule" : true,
					"minimumCMakeVersion" : 
					{
						"string" : "3.13"
					},
					"projectIndex" : 0,
					"source" : ".",
					"targetIndexes" : 
					[
						1,
						9
					]
				},
				{
					"build" : "_deps/mahi-gui-build",
					"childIndexes" : 
					[
						2,
						4,
						5,
						7,
						8,
						9,
						16
					],
					"hasInstallRule" : true,
					"minimumCMakeVersion" : 
					{
						"string" : "3.13.0"
					},
					"parentIndex" : 0,
					"projectIndex" : 1,
					"source" : "build/_deps/mahi-gui-src",
					"targetIndexes" : 
					[
						5
					]
				},
				{
					"build" : "_deps/mahi-gui-build/3rdparty/glfw",
					"childIndexes" : 
					[
						3
					],
					"hasInstallRule" : true,
					"minimumCMakeVersion" : 
					{
						"string" : "3.1"
					},
					"parentIndex" : 1,
					"projectIndex" : 2,
					"source" : "build/_deps/mahi-gui-src/3rdparty/glfw",
					"targetIndexes" : 
					[
						10
					]
				},
				{
					"build" : "_deps/mahi-gui-build/3rdparty/glfw/src",
					"hasInstallRule" : true,
					"minimumCMakeVersion" : 
					{
						"string" : "3.1"
					},
					"parentIndex" : 2,
					"projectIndex" : 2,
					"source" : "build/_deps/mahi-gui-src/3rdparty/glfw/src",
					"targetIndexes" : 
					[
						4
					]
				},
				{
					"build" : "_deps/mahi-gui-build/3rdparty/glad",
					"minimumCMakeVersion" : 
					{
						"string" : "3.13.0"
					},
					"parentIndex" : 1,
					"projectIndex" : 1,
					"source" : "build/_deps/mahi-gui-src/3rdparty/glad",
					"targetIndexes" : 
					[
						3
					]
				},
				{
					"build" : "_deps/mahi-gui-build/3rdparty/nativefiledialog-extended",
					"childIndexes" : 
					[
						6
					],
					"minimumCMakeVersion" : 
					{
						"string" : "3.2"
					},
					"parentIndex" : 1,
					"projectIndex" : 3,
					"source" : "build/_deps/mahi-gui-src/3rdparty/nativefiledialog-extended"
				},
				{
					"build" : "_deps/mahi-gui-build/3rdparty/nativefiledialog-extended/src",
					"minimumCMakeVersion" : 
					{
						"string" : "3.2"
					},
					"parentIndex" : 5,
					"projectIndex" : 3,
					"source" : "build/_deps/mahi-gui-src/3rdparty/nativefiledialog-extended/src",
					"targetIndexes" : 
					[
						8
					]
				},
				{
					"build" : "_deps/mahi-gui-build/3rdparty/nanovg",
					"minimumCMakeVersion" : 
					{
						"string" : "3.13.0"
					},
					"parentIndex" : 1,
					"projectIndex" : 1,
					"source" : "build/_deps/mahi-gui-src/3rdparty/nanovg",
					"targetIndexes" : 
					[
						6,
						7
					]
				},
				{
					"build" : "_deps/mahi-gui-build/3rdparty/clipper",
					"minimumCMakeVersion" : 
					{
						"string" : "3.13.0"
					},
					"parentIndex" : 1,
					"projectIndex" : 1,
					"source" : "build/_deps/mahi-gui-src/3rdparty/clipper",
					"targetIndexes" : 
					[
						0
					]
				},
				{
					"build" : "_deps/mahi-util-build",
					"childIndexes" : 
					[
						10,
						11
					],
					"hasInstallRule" : true,
					"minimumCMakeVersion" : 
					{
						"string" : "3.13.0"
					},
					"parentIndex" : 1,
					"projectIndex" : 4,
					"source" : "build/_deps/mahi-util-src",
					"targetIndexes" : 
					[
						11
					]
				},
				{
					"build" : "_deps/mahi-util-build/3rdparty/fmt",
					"minimumCMakeVersion" : 
					{
						"string" : "3.1.0"
					},
					"parentIndex" : 9,
					"projectIndex" : 5,
					"source" : "build/_deps/mahi-util-src/3rdparty/fmt",
					"targetIndexes" : 
					[
						2
					]
				},
				{
					"build" : "_deps/mahi-util-build/src/Mahi/Util",
					"childIndexes" : 
					[
						12,
						13,
						14,
						15
					],
					"minimumCMakeVersion" : 
					{
						"string" : "3.13.0"
					},
					"parentIndex" : 9,
					"projectIndex" : 4,
					"source" : "build/_deps/mahi-util-src/src/Mahi/Util"
				},
				{
					"build" : "_deps/mahi-util-build/src/Mahi/Util/Concurrency",
					"minimumCMakeVersion" : 
					{
						"string" : "3.13.0"
					},
					"parentIndex" : 11,
					"projectIndex" : 4,
					"source" : "build/_deps/mahi-util-src/src/Mahi/Util/Concurrency"
				},
				{
					"build" : "_deps/mahi-util-build/src/Mahi/Util/Logging",
					"minimumCMakeVersion" : 
					{
						"string" : "3.13.0"
					},
					"parentIndex" : 11,
					"projectIndex" : 4,
					"source" : "build/_deps/mahi-util-src/src/Mahi/Util/Logging"
				},
				{
					"build" : "_deps/mahi-util-build/src/Mahi/Util/Math",
					"minimumCMakeVersion" : 
					{
						"string" : "3.13.0"
					},
					"parentIndex" : 11,
					"projectIndex" : 4,
					"source" : "build/_deps/mahi-util-src/src/Mahi/Util/Math"
				},
				{
					"build" : "_deps/mahi-util-build/src/Mahi/Util/Timing",
					"minimumCMakeVersion" : 
					{
						"string" : "3.13.0"
					},
					"parentIndex" : 11,
					"projectIndex" : 4,
					"source" : "build/_deps/mahi-util-src/src/Mahi/Util/Timing"
				},
				{
					"build" : "_deps/mahi-gui-build/src/Mahi/Gui",
					"childIndexes" : 
					[
						17
					],
					"minimumCMakeVersion" : 
					{
						"string" : "3.13.0"
					},
					"parentIndex" : 1,
					"projectIndex" : 1,
					"source" : "build/_deps/mahi-gui-src/src/Mahi/Gui"
				},
				{
					"build" : "_deps/mahi-gui-build/src/Mahi/Gui/Fonts",
					"minimumCMakeVersion" : 
					{
						"string" : "3.13.0"
					},
					"parentIndex" : 16,
					"projectIndex" : 1,
					"source" : "build/_deps/mahi-gui-src/src/Mahi/Gui/Fonts"
				}
			],
			"name" : "Release",
			"projects" : 
			[
				{
					"childIndexes" : 
					[
						1
					],
					"directoryIndexes" : 
					[
						0
					],
					"name" : "ControlGUI",
					"targetIndexes" : 
					[
						1,
						9
					]
				},
				{
					"childIndexes" : 
					[
						2,
						3,
						4
					],
					"directoryIndexes" : 
					[
						1,
						4,
						7,
						8,
						16,
						17
					],
					"name" : "mahi-gui",
					"parentIndex" : 0,
					"targetIndexes" : 
					[
						0,
						3,
						5,
						6,
						7
					]
				},
				{
					"directoryIndexes" : 
					[
						2,
						3
					],
					"name" : "GLFW",
					"parentIndex" : 1,
					"targetIndexes" : 
					[
						4,
						10
					]
				},
				{
					"directoryIndexes" : 
					[
						5,
						6
					],
					"name" : "nativefiledialog-extended",
					"parentIndex" : 1,
					"targetIndexes" : 
					[
						8
					]
				},
				{
					"childIndexes" : 
					[
						5
					],
					"directoryIndexes" : 
					[
						9,
						11,
						12,
						13,
						14,
						15
					],
					"name" : "mahi-util",
					"parentIndex" : 1,
					"targetIndexes" : 
					[
						11
					]
				},
				{
					"directoryIndexes" : 
					[
						10
					],
					"name" : "FMT",
					"parentIndex" : 4,
					"targetIndexes" : 
					[
						2
					]
				}
			],
			"targets" : 
			[
				{
					"directoryIndex" : 8,
					"id" : "clipper::@ee099ffbe401603287c6",
					"jsonFile" : "target-clipper-Release-aa52dc5424f1e9b0b0a2.json",
					"name" : "clipper",
					"projectIndex" : 1
				},
				{
					"directoryIndex" : 0,
					"id" : "control_gui::@6890427a1f51a3e7e1df",
					"jsonFile" : "target-control_gui-Release-b0bbef85d11d12ab031e.json",
					"name" : "control_gui",
					"projectIndex" : 0
				},
				{
					"directoryIndex" : 10,
					"id" : "fmt::@1dc5051ce61772968524",
					"jsonFile" : "target-fmt-Release-ebe834a381d39e0068e0.json",
					"name" : "fmt",
					"projectIndex" : 5
				},
				{
					"directoryIndex" : 4,
					"id" : "glad::@8ab0b9cb3b88849ec662",
					"jsonFile" : "target-glad-Release-5b772a388c833c10c566.json",
					"name" : "glad",
					"projectIndex" : 1
				},
				{
					"directoryIndex" : 3,
					"id" : "glfw::@292da2318190b66a3baa",
					"jsonFile" : "target-glfw-Release-00d7e96196f61e567cdd.json",
					"name" : "glfw",
					"projectIndex" : 2
				},
				{
					"directoryIndex" : 1,
					"id" : "gui::@b89b3f0f161a861a84d0",
					"jsonFile" : "target-gui-Release-d07157bf951f79355e1f.json",
					"name" : "gui",
					"projectIndex" : 1
				},
				{
					"directoryIndex" : 7,
					"id" : "nanovg::@c7daccaf0a7753883acf",
					"jsonFile" : "target-nanovg-Release-70da234e2da63b07c357.json",
					"name" : "nanovg",
					"projectIndex" : 1
				},
				{
					"directoryIndex" : 7,
					"id" : "nanovg-fbo::@c7daccaf0a7753883acf",
					"jsonFile" : "target-nanovg-fbo-Release-1be3d8d35a3727f0a1e0.json",
					"name" : "nanovg-fbo",
					"projectIndex" : 1
				},
				{
					"directoryIndex" : 6,
					"id" : "nfd::@3b80e14ecf71f20e142b",
					"jsonFile" : "target-nfd-Release-60e45539fab2357c833b.json",
					"name" : "nfd",
					"projectIndex" : 3
				},
				{
					"directoryIndex" : 0,
					"id" : "serial_test::@6890427a1f51a3e7e1df",
					"jsonFile" : "target-serial_test-Release-5b7971b234051ea9485c.json",
					"name" : "serial_test",
					"projectIndex" : 0
				},
				{
					"directoryIndex" : 2,
					"id" : "uninstall::@bb8c698527e6e1f6c780",
					"jsonFile" : "target-uninstall-Release-11ec04421ff1d1a678ad.json",
					"name" : "uninstall",
					"projectIndex" : 2
				},
				{
					"directoryIndex" : 9,
					"id" : "util::@9e7e004084100b3727b4",
					"jsonFile" : "target-util-Release-e1cfeda0a730584c6741.json",
					"name" : "util",
					"projectIndex" : 4
				}
			]
		}
	],
	"kind" : "codemodel",
	"paths" : 
	{
		"build" : "C:/Git/RobotControl/Code/ControlGUI/build",
		"source" : "C:/Git/RobotControl/Code/ControlGUI"
	},
	"version" : 
	{
		"major" : 2,
		"minor" : 0
	}
}
